replitapi/__init__.py
replitapi/database/__init__.py
replitapi/database/database.py
replitapi/database/default_db.py
replitapi/database/server.py
replitapi_JustFinnbarM-0.0.1.dist-info/LICENSE
replitapi_JustFinnbarM-0.0.1.dist-info/METADATA
replitapi_JustFinnbarM-0.0.1.dist-info/WHEEL
replitapi_JustFinnbarM-0.0.1.dist-info/top_level.txt
replitapi_JustFinnbarM-0.0.1.dist-info/RECORD
