Metadata-Version: 2.1
Name: replitapi-JustFinnbarM
Version: 0.0.1
Summary: Tools for interacting with the replit site and database that do not depend on an ancient version of Flask.
Home-page: https://replit.com/@xfinnbar/Replit-API
Author: Finnbar M
Author-email: xfinnbar@gmail.com
License: UNKNOWN
Platform: UNKNOWN
Classifier: Programming Language :: Python :: 3
Classifier: License :: OSI Approved :: MIT License
Classifier: Operating System :: OS Independent
Requires-Python: >=3.7
Requires-Dist: requests
Requires-Dist: bs4
